{
  "1_intro": [
    {
      "source": "print(\"hello world!\")",
      "names": [
        {
          "import_components": [
            "print"
          ],
          "code_str": "print",
          "lineno": 1,
          "end_lineno": 1,
          "context": "none",
          "resolved_location": "print"
        }
      ],
      "example": {
        "document": "1_intro",
        "ref_id": "Title-of-Intro",
        "headings": [
          "Title of Intro"
        ]
      },
      "doc_lineno": null
    },
    {
      "source": "import tensorflow as tf\nprint(\"TensorFlow version:\", tf.__version__)",
      "names": [
        {
          "import_components": [
            "print"
          ],
          "code_str": "print",
          "lineno": 2,
          "end_lineno": 2,
          "context": "none",
          "resolved_location": "print"
        }
      ],
      "example": {
        "document": "1_intro",
        "ref_id": "Title-of-Intro",
        "headings": [
          "Title of Intro"
        ]
      },
      "doc_lineno": null
    }
  ],
  "index": []
}